pyxas/__init__.py
pyxas/align3D.py
pyxas/align_rot.py
pyxas/align_tomo_proj.py
pyxas/colormix.py
pyxas/image_util.py
pyxas/lsq_fit.py
pyxas/misc.py
pyxas/xanes_fit.py
pyxas/xanes_util.py
pyxas-1.0.data/scripts/pyxas_gui
pyxas-1.0.dist-info/LICENSE
pyxas-1.0.dist-info/METADATA
pyxas-1.0.dist-info/WHEEL
pyxas-1.0.dist-info/top_level.txt
pyxas-1.0.dist-info/RECORD
